MUX21.v
module MUX21(
    input [15:0] i0,
    input [15:0] i1,
    input sel,
    output [15:0] out
);
    assign out = sel? i1:i0;

endmodule

MUX41/MUX41.v
module MUX41 (
    input [15:0] i0,
    input [15:0] i1,
    input [15:0] i2,
    input [15:0] i3,
    input [1:0] sel,
    output reg [15:0] out
);

always@(*)begin
    case(sel)
        0 : out <= i0;
        1 : out <= i1;
        2 : out <= i2;
        3 : out <= i3;
        default : out <= 0;

    endcase
end
    
endmodule

REGISTER 16/REG16.v
module REG16(
    input clk,
    input rst,
    input ld,
    input [15:0] data_in,
    output reg [15:0] q
);

initial begin
    q = 0;
end

always @(posedge clk) begin
    if(rst) q <= 0;
    else begin
        if(ld) q <= data_in;
        else q <= q;
    end
end

endmodule

CONTROL.v
module CONTROL(
    input clk,
    input start,
    input lt,
    output reg rd, wr, operation, clr,preset,
    output reg m3_sel, m5_sel, m6_sel,
    output reg [1:0] m1_sel, m4_sel, m2_sel,
    output reg ln, li, lj, lk, la, lb,
    output [3:0] state_out
);
    // output reg state_out
    reg [3:0] state;
    initial begin
        state = 0;
        {rd, wr, operation,clr, preset,m3_sel,m5_sel,m6_sel} = 8'b0;
        m1_sel = 0;
        m4_sel = 0;
        m2_sel = 0;
        {ln,li,lj,lk,la,lb} <= 6'b0;
    end

    // actions performed in specific state
    always @(*) begin
        case(state)
        0: begin
            {ln,li,lj,lk,la,lb} <= 6'b0;
        end
        1: begin
            clr <= 1;
            m6_sel <= 0;
            lj <= 1;
        end

        2: begin
            clr <=0;
            {ln,li,lj,lk,la,lb} <= 6'b0;
            m1_sel <=1;
            m2_sel <= 0;
            operation <= 0;
        end

        3: begin
            li <= 1;
            m5_sel <= 0;
        end

        4: begin
            {ln,li,lj,lk,la,lb} <= 6'b0;
            m1_sel <= 0;
            m2_sel <= 0;
            operation <= 0;
        end

        5: begin
            la <=1;
            m4_sel <=0;
            rd <= 1;
            m1_sel <= 0;
            m2_sel <= 2;
            operation <= 1;
            lk <= 1;
        end

        6: begin
            la <= 0;
            lk <= 0;
            m4_sel <= 2;
            rd <= 1;
            lb <= 1;
        end

        7: begin
            {ln,li,lj,lk,la,lb} <= 6'b0;
            rd <= 0;
            m1_sel <= 2;
            m2_sel <= 1;
            operation <= 0;
        end

        8: begin
            {ln,li,lj,lk,la,lb} <= 6'b0;
            m4_sel <=0;
            m3_sel <= 1;
            wr <= 1;
        end

        9: begin
            {ln,li,lj,lk,la,lb} <= 6'b0;
            m4_sel <= 2;
            m3_sel <= 0;
            wr <= 1;
        end

        10: begin
            wr <= 0;
            m1_sel <= 0;
            m2_sel <= 2;
            operation <= 1;
            m5_sel <= 1;
            li <= 1;
        end

        11: begin
            li <= 0;
            lj<= 0;
            m1_sel <= 1;
            m2_sel <= 2;
            operation <= 1;
            m6_sel <= 1;
        end

        12: begin
            preset <= 1;
        end

        endcase
    end


    // assignment of next states
    always @(posedge clk) begin
        case(state)

        //RESET STATE
        0: begin
            if(start) state <= 1;
            else state <= state;
        end

        1: begin
            state <= 2;
        end

        2: begin
            if(lt) state <= 3;
            else state <= 12;
        end

        3: begin
            state <= 4;
        end

        4: begin
            if(lt) state <= 5;
            else state <= 11;
        end

        5: begin
            state <= 6;
        end

        6: begin
            state <= 7;
        end

        7: begin
            if (lt) state <= 8;
            else state <= 10;
        end

        8: begin
            state <= 9;
        end

        9: begin
            state <= 10;
        end

        10: begin
            state <= 4;
        end

        11: begin
            state <= 2;
            
        end

        12: begin
            if(start) state <= state;
            else state <= 0;
        end

        endcase
    end

    assign state_out = state;



endmodule

ALU/ALU.v
module ALU (
    input [15:0] op1,
    input [15:0] op2,
    input operation,
    output reg lt,
    output reg [15:0] result

);

//operation : 0-> compare, 1-> add
// lt : (op1<op2)? 1:0;

always @(*) begin
    if(operation) begin
        result = op1 + op2;
        lt = 1'bz;
    end
    else begin
        result = 16'bz;
        lt = (op1<op2);
    end
end


endmodule

MEM.v
module RAM(
    input clk,
    input [15:0] data_in,
    input rd,
    input wr,
    input [9:0] address,
    output [15:0] data_out
);

    //1k memory with word size of 16 bits.
    reg [15:0] ram [0:1023];

    always @(posedge clk) begin
        if(wr)
        ram[address] <= data_in;
    end
    assign data_out = (rd) ? ram[address] : 16'bzzzzzzzzzzzzzzzz;
    

endmodule

BUBBLESORT.v
module bubblesort (
    input clk,
    input start,
    output complete,
    output [3:0] state_out
);

    // data_n1 => length of array to be sorted.
    reg [15:0] data_n1;
    reg rst;
    initial begin
        data_n1 = 16'd7;
        rst = 0;    
    end

    // wires
    wire rd, wr, operation, clr,preset;
    wire m3_sel, m5_sel, m6_sel;
    wire [1:0] m1_sel, m4_sel, m2_sel;
    wire ln, li, lj, lk, la, lb;
    wire [15:0] data_in, data_out, result;
    wire [15:0] address;
    wire [15:0] op1, op2;
    wire lt;
    wire [15:0] m5_out, m6_out;
    wire [15:0] n_out, i_out, j_out, k_out, a_out, b_out;

    //END of Code block
    reg eoc;
    initial begin
        eoc = 0;
    end

    //Instansiating modules
    RAM MEM(clk, data_in ,rd, wr, address[9:0], data_out);
    ALU alu(op1, op2, operation, lt, result);
    CONTROL CU(clk, start,lt,
            rd, wr, operation, clr, preset,
            m3_sel, m5_sel, m6_sel,
            m1_sel, m4_sel, m2_sel,
            ln, li, lj, lk, la, lb,
            state_out
    );

    // registers
    REG16 n1(clk,rst,1'b1, data_n1, n_out);
    REG16 i(clk,rst,li, m5_out, i_out);
    REG16 j(clk,rst,lj, m6_out, j_out);
    REG16 k(clk,rst,lk, result, k_out);
    REG16 a(clk,rst,la, data_out, a_out);
    REG16 b(clk,rst,lb, data_out, b_out);


    // MUX
    MUX41 m1(i_out, j_out,a_out, 16'b0, m1_sel,op1);
    MUX41 m2(n_out, b_out, 16'd1 , 16'b0, m2_sel, op2);
    MUX21 m3(a_out, b_out, m3_sel, data_in);
    MUX41 m4(i_out, j_out, k_out, 16'b0, m4_sel, address);
    MUX21 m5(16'b0, result, m5_sel, m5_out);
    MUX21 m6(16'b0, result, m6_sel, m6_out);

    //EOC Block
    always @(*) begin
        if(clr) eoc <= 0;
        else if (preset) eoc<=1;
        else eoc <= eoc;
    end
    assign complete = eoc;

endmodule

BUBBLESORT_TB.v
`timescale 1ns/1ps

module bubblesort_tb ();
    reg clk;
    reg start;
    wire complete;
    wire [3:0] state_out;

    bubblesort UUT(clk, start, complete, state_out);
    
    initial begin
        $dumpfile("wave_bub.vcd");
        $dumpvars(0,bubblesort_tb);
    end

    initial begin

        //Replace "Data.txt" with the file containing unsorted elements.
        $readmemh("Data.txt",UUT.MEM.ram);

        clk = 0;
        start = 0;

        #10
        start = 1;

        //provide sufficient time to complete the sorting
        #4000
        //Getting output in "out.txt" file
        $writememh("out.txt",UUT.MEM.ram);
        #10
        $finish;
    end
    // giving clock of Timeperiod = 10 ns
    always clk = #5 ~clk;
endmodule

wave_bub.vcd
$date
	Sun Aug 20 23:59:52 2023
$end
$version
	Icarus Verilog
$end
$timescale
	1ps
$end
$scope module bubblesort_tb $end
$var wire 4 ! state_out [3:0] $end
$var wire 1 " complete $end
$var reg 1 # clk $end
$var reg 1 $ start $end
$scope module UUT $end
$var wire 1 # clk $end
$var wire 1 " complete $end
$var wire 1 $ start $end
$var wire 1 % wr $end
$var wire 4 & state_out [3:0] $end
$var wire 16 ' result [15:0] $end
$var wire 1 ( rd $end
$var wire 1 ) preset $end
$var wire 1 * operation $end
$var wire 16 + op2 [15:0] $end
$var wire 16 , op1 [15:0] $end
$var wire 16 - n_out [15:0] $end
$var wire 1 . m6_sel $end
$var wire 16 / m6_out [15:0] $end
$var wire 1 0 m5_sel $end
$var wire 16 1 m5_out [15:0] $end
$var wire 2 2 m4_sel [1:0] $end
$var wire 1 3 m3_sel $end
$var wire 2 4 m2_sel [1:0] $end
$var wire 2 5 m1_sel [1:0] $end
$var wire 1 6 lt $end
$var wire 1 7 ln $end
$var wire 1 8 lk $end
$var wire 1 9 lj $end
$var wire 1 : li $end
$var wire 1 ; lb $end
$var wire 1 < la $end
$var wire 16 = k_out [15:0] $end
$var wire 16 > j_out [15:0] $end
$var wire 16 ? i_out [15:0] $end
$var wire 16 @ data_out [15:0] $end
$var wire 16 A data_in [15:0] $end
$var wire 1 B clr $end
$var wire 16 C b_out [15:0] $end
$var wire 16 D address [15:0] $end
$var wire 16 E a_out [15:0] $end
$var reg 16 F data_n1 [15:0] $end
$var reg 1 G eoc $end
$var reg 1 H rst $end
$scope module CU $end
$var wire 1 # clk $end
$var wire 1 $ start $end
$var wire 4 I state_out [3:0] $end
$var wire 1 6 lt $end
$var reg 1 B clr $end
$var reg 1 < la $end
$var reg 1 ; lb $end
$var reg 1 : li $end
$var reg 1 9 lj $end
$var reg 1 8 lk $end
$var reg 1 7 ln $end
$var reg 2 J m1_sel [1:0] $end
$var reg 2 K m2_sel [1:0] $end
$var reg 1 3 m3_sel $end
$var reg 2 L m4_sel [1:0] $end
$var reg 1 0 m5_sel $end
$var reg 1 . m6_sel $end
$var reg 1 * operation $end
$var reg 1 ) preset $end
$var reg 1 ( rd $end
$var reg 4 M state [3:0] $end
$var reg 1 % wr $end
$upscope $end
$scope module MEM $end
$var wire 10 N address [9:0] $end
$var wire 1 # clk $end
$var wire 1 ( rd $end
$var wire 1 % wr $end
$var wire 16 O data_out [15:0] $end
$var wire 16 P data_in [15:0] $end
$upscope $end
$scope module a $end
$var wire 1 # clk $end
$var wire 16 Q data_in [15:0] $end
$var wire 1 < ld $end
$var wire 1 H rst $end
$var reg 16 R q [15:0] $end
$upscope $end
$scope module alu $end
$var wire 1 * operation $end
$var wire 16 S op2 [15:0] $end
$var wire 16 T op1 [15:0] $end
$var reg 1 6 lt $end
$var reg 16 U result [15:0] $end
$upscope $end
$scope module b $end
$var wire 1 # clk $end
$var wire 16 V data_in [15:0] $end
$var wire 1 ; ld $end
$var wire 1 H rst $end
$var reg 16 W q [15:0] $end
$upscope $end
$scope module i $end
$var wire 1 # clk $end
$var wire 1 : ld $end
$var wire 1 H rst $end
$var wire 16 X data_in [15:0] $end
$var reg 16 Y q [15:0] $end
$upscope $end
$scope module j $end
$var wire 1 # clk $end
$var wire 1 9 ld $end
$var wire 1 H rst $end
$var wire 16 Z data_in [15:0] $end
$var reg 16 [ q [15:0] $end
$upscope $end
$scope module k $end
$var wire 1 # clk $end
$var wire 16 \ data_in [15:0] $end
$var wire 1 8 ld $end
$var wire 1 H rst $end
$var reg 16 ] q [15:0] $end
$upscope $end
$scope module m1 $end
$var wire 16 ^ i0 [15:0] $end
$var wire 16 _ i1 [15:0] $end
$var wire 16 ` i2 [15:0] $end
$var wire 16 a i3 [15:0] $end
$var wire 2 b sel [1:0] $end
$var reg 16 c out [15:0] $end
$upscope $end
$scope module m2 $end
$var wire 16 d i1 [15:0] $end
$var wire 16 e i2 [15:0] $end
$var wire 16 f i3 [15:0] $end
$var wire 2 g sel [1:0] $end
$var wire 16 h i0 [15:0] $end
$var reg 16 i out [15:0] $end
$upscope $end
$scope module m3 $end
$var wire 16 j i0 [15:0] $end
$var wire 16 k i1 [15:0] $end
$var wire 1 3 sel $end
$var wire 16 l out [15:0] $end
$upscope $end
$scope module m4 $end
$var wire 16 m i0 [15:0] $end
$var wire 16 n i1 [15:0] $end
$var wire 16 o i2 [15:0] $end
$var wire 16 p i3 [15:0] $end
$var wire 2 q sel [1:0] $end
$var reg 16 r out [15:0] $end
$upscope $end
$scope module m5 $end
$var wire 16 s i0 [15:0] $end
$var wire 16 t i1 [15:0] $end
$var wire 1 0 sel $end
$var wire 16 u out [15:0] $end
$upscope $end
$scope module m6 $end
$var wire 16 v i0 [15:0] $end
$var wire 16 w i1 [15:0] $end
$var wire 1 . sel $end
$var wire 16 x out [15:0] $end
$upscope $end
$scope module n1 $end
$var wire 1 # clk $end
$var wire 16 y data_in [15:0] $end
$var wire 1 z ld $end
$var wire 1 H rst $end
$var reg 16 { q [15:0] $end
$upscope $end
$upscope $end
$upscope $end
$enddefinitions $end
#0
$dumpvars
b0 {
1z
b111 y
b0 x
bz w
b0 v
b0 u
bz t
b0 s
b0 r
b0 q
b0 p
b0 o
b0 n
b0 m
b0 l
b0 k
b0 j
b0 i
b0 h
b0 g
b0 f
b1 e
b0 d
b0 c
b0 b
b0 a
b0 `
b0 _
b0 ^
b0 ]
bz \
b0 [
b0 Z
b0 Y
b0 X
b0 W
bz V
bz U
b0 T
b0 S
b0 R
bz Q
b0 P
bz O
b0 N
b0 M
b0 L
b0 K
b0 J
b0 I
0H
0G
b111 F
b0 E
b0 D
b0 C
0B
b0 A
bz @
b0 ?
b0 >
b0 =
0<
0;
0:
09
08
07
06
b0 5
b0 4
03
b0 2
b0 1
00
b0 /
0.
b0 -
b0 ,
b0 +
0*
0)
0(
bz '
b0 &
0%
0$
0#
0"
b0 !
$end
#5000
16
b111 +
b111 S
b111 i
b111 -
b111 h
b111 {
1#
#10000
0#
1$
#15000
19
1B
b1 !
b1 &
b1 I
b1 M
1#
#20000
0#
#25000
b1 5
b1 J
b1 b
09
0B
b10 !
b10 &
b10 I
b10 M
1#
#30000
0#
#35000
1:
b11 !
b11 &
b11 I
b11 M
1#
#40000
0#
#45000
b0 5
b0 J
b0 b
0:
b100 !
b100 &
b100 I
b100 M
1#
#50000
0#
#55000
b1 +
b1 S
b1 i
z6
b1 '
b1 U
b1 \
b1 t
b1 w
b11010 @
b11010 O
b11010 Q
b11010 V
18
1*
b10 4
b10 K
b10 g
1(
1<
b101 !
b101 &
b101 I
b101 M
1#
#60000
0#
#65000
b111000000000000 @
b111000000000000 O
b111000000000000 Q
b111000000000000 V
b1 N
b1 D
b1 r
1;
b10 2
b10 L
b10 q
08
0<
b11010 A
b11010 P
b11010 l
b110 !
b110 &
b110 I
b110 M
b1 =
b1 ]
b1 o
b11010 E
b11010 R
b11010 `
b11010 j
1#
#70000
0#
#75000
b111000000000000 +
b111000000000000 S
b111000000000000 i
b11010 ,
b11010 T
b11010 c
16
bz '
bz U
bz \
bz t
bz w
bz @
bz O
bz Q
bz V
0*
b1 4
b1 K
b1 g
b10 5
b10 J
b10 b
0(
0;
b111000000000000 C
b111000000000000 W
b111000000000000 d
b111000000000000 k
b111 !
b111 &
b111 I
b111 M
1#
#80000
0#
#85000
b0 N
b0 D
b0 r
b111000000000000 A
b111000000000000 P
b111000000000000 l
1%
13
b0 2
b0 L
b0 q
b1000 !
b1000 &
b1000 I
b1000 M
1#
#90000
0#
#95000
b1 N
b1 D
b1 r
b11010 A
b11010 P
b11010 l
03
b10 2
b10 L
b10 q
b1001 !
b1001 &
b1001 I
b1001 M
1#
#100000
0#
#105000
b1 +
b1 S
b1 i
b0 ,
b0 T
b0 c
b1 1
b1 X
b1 u
z6
b1 '
b1 U
b1 \
b1 t
b1 w
1:
10
1*
b10 4
b10 K
b10 g
b0 5
b0 J
b0 b
0%
b1010 !
b1010 &
b1010 I
b1010 M
1#
#110000
0#
#115000
b111 +
b111 S
b111 i
bz 1
bz X
bz u
16
bz '
bz U
bz \
bz t
bz w
b1 ,
b1 T
b1 c
0*
b0 4
b0 K
b0 g
0:
b1 ?
b1 Y
b1 ^
b1 m
b100 !
b100 &
b100 I
b100 M
1#
#120000
0#
#125000
b1 +
b1 S
b1 i
b10 1
b10 X
b10 u
z6
b10 '
b10 U
b10 \
b10 t
b10 w
b11010 @
b11010 O
b11010 Q
b11010 V
18
1*
b10 4
b10 K
b10 g
1(
b0 2
b0 L
b0 q
1<
b101 !
b101 &
b101 I
b101 M
1#
#130000
0#
#135000
b10001 @
b10001 O
b10001 Q
b10001 V
b10 N
b10 D
b10 r
1;
b10 2
b10 L
b10 q
08
0<
b10 =
b10 ]
b10 o
b110 !
b110 &
b110 I
b110 M
1#
#140000
0#
#145000
b10001 +
b10001 S
b10001 i
b11010 ,
b11010 T
b11010 c
bz 1
bz X
bz u
06
bz '
bz U
bz \
bz t
bz w
bz @
bz O
bz Q
bz V
0*
b1 4
b1 K
b1 g
b10 5
b10 J
b10 b
0(
0;
b111 !
b111 &
b111 I
b111 M
b10001 C
b10001 W
b10001 d
b10001 k
1#
#150000
0#
#155000
b1 +
b1 S
b1 i
b1 ,
b1 T
b1 c
b10 1
b10 X
b10 u
z6
b10 '
b10 U
b10 \
b10 t
b10 w
1:
1*
b10 4
b10 K
b10 g
b0 5
b0 J
b0 b
b1010 !
b1010 &
b1010 I
b1010 M
1#
#160000
0#
#165000
b111 +
b111 S
b111 i
bz 1
bz X
bz u
16
bz '
bz U
bz \
bz t
bz w
0*
b0 4
b0 K
b0 g
0:
b10 ,
b10 T
b10 c
b100 !
b100 &
b100 I
b100 M
b10 ?
b10 Y
b10 ^
b10 m
1#
#170000
0#
#175000
b1 +
b1 S
b1 i
b11 1
b11 X
b11 u
z6
b11 '
b11 U
b11 \
b11 t
b11 w
b10001 @
b10001 O
b10001 Q
b10001 V
18
1*
b10 4
b10 K
b10 g
1(
b0 2
b0 L
b0 q
1<
b101 !
b101 &
b101 I
b101 M
1#
#180000
0#
#185000
b0 @
b0 O
b0 Q
b0 V
b11 N
b11 D
b11 r
1;
b10 2
b10 L
b10 q
08
0<
b10001 A
b10001 P
b10001 l
b110 !
b110 &
b110 I
b110 M
b11 =
b11 ]
b11 o
b10001 E
b10001 R
b10001 `
b10001 j
1#
#190000
0#
#195000
b0 +
b0 S
b0 i
b10001 ,
b10001 T
b10001 c
bz 1
bz X
bz u
06
bz '
bz U
bz \
bz t
bz w
bz @
bz O
bz Q
bz V
0*
b1 4
b1 K
b1 g
b10 5
b10 J
b10 b
0(
0;
b0 C
b0 W
b0 d
b0 k
b111 !
b111 &
b111 I
b111 M
1#
#200000
0#
#205000
b1 +
b1 S
b1 i
b10 ,
b10 T
b10 c
b11 1
b11 X
b11 u
z6
b11 '
b11 U
b11 \
b11 t
b11 w
1:
1*
b10 4
b10 K
b10 g
b0 5
b0 J
b0 b
b1010 !
b1010 &
b1010 I
b1010 M
1#
#210000
0#
#215000
b111 +
b111 S
b111 i
bz 1
bz X
bz u
16
bz '
bz U
bz \
bz t
bz w
b11 ,
b11 T
b11 c
0*
b0 4
b0 K
b0 g
0:
b11 ?
b11 Y
b11 ^
b11 m
b100 !
b100 &
b100 I
b100 M
1#
#220000
0#
#225000
b1 +
b1 S
b1 i
b100 1
b100 X
b100 u
z6
b100 '
b100 U
b100 \
b100 t
b100 w
b0 @
b0 O
b0 Q
b0 V
18
1*
b10 4
b10 K
b10 g
1(
b0 2
b0 L
b0 q
1<
b101 !
b101 &
b101 I
b101 M
1#
#230000
0#
#235000
b1110010101000101 @
b1110010101000101 O
b1110010101000101 Q
b1110010101000101 V
b100 N
b100 D
b100 r
1;
b10 2
b10 L
b10 q
08
0<
b0 A
b0 P
b0 l
b0 E
b0 R
b0 `
b0 j
b100 =
b100 ]
b100 o
b110 !
b110 &
b110 I
b110 M
1#
#240000
0#
#245000
b1110010101000101 +
b1110010101000101 S
b1110010101000101 i
b0 ,
b0 T
b0 c
bz 1
bz X
bz u
16
bz '
bz U
bz \
bz t
bz w
bz @
bz O
bz Q
bz V
0*
b1 4
b1 K
b1 g
b10 5
b10 J
b10 b
0(
0;
b111 !
b111 &
b111 I
b111 M
b1110010101000101 C
b1110010101000101 W
b1110010101000101 d
b1110010101000101 k
1#
#250000
0#
#255000
b11 N
b11 D
b11 r
b1110010101000101 A
b1110010101000101 P
b1110010101000101 l
1%
13
b0 2
b0 L
b0 q
b1000 !
b1000 &
b1000 I
b1000 M
1#
#260000
0#
#265000
b100 N
b100 D
b100 r
b0 A
b0 P
b0 l
03
b10 2
b10 L
b10 q
b1001 !
b1001 &
b1001 I
b1001 M
1#
#270000
0#
#275000
b1 +
b1 S
b1 i
b11 ,
b11 T
b11 c
b100 1
b100 X
b100 u
z6
b100 '
b100 U
b100 \
b100 t
b100 w
1:
1*
b10 4
b10 K
b10 g
b0 5
b0 J
b0 b
0%
b1010 !
b1010 &
b1010 I
b1010 M
1#
#280000
0#
#285000
b111 +
b111 S
b111 i
bz 1
bz X
bz u
16
bz '
bz U
bz \
bz t
bz w
0*
b0 4
b0 K
b0 g
0:
b100 ,
b100 T
b100 c
b100 !
b100 &
b100 I
b100 M
b100 ?
b100 Y
b100 ^
b100 m
1#
#290000
0#
#295000
b1 +
b1 S
b1 i
b101 1
b101 X
b101 u
z6
b101 '
b101 U
b101 \
b101 t
b101 w
b0 @
b0 O
b0 Q
b0 V
18
1*
b10 4
b10 K
b10 g
1(
b0 2
b0 L
b0 q
1<
b101 !
b101 &
b101 I
b101 M
1#
#300000
0#
#305000
b1000000000 @
b1000000000 O
b1000000000 Q
b1000000000 V
b101 N
b101 D
b101 r
1;
b10 2
b10 L
b10 q
08
0<
b110 !
b110 &
b110 I
b110 M
b101 =
b101 ]
b101 o
1#
#310000
0#
#315000
b1000000000 +
b1000000000 S
b1000000000 i
b0 ,
b0 T
b0 c
bz 1
bz X
bz u
16
bz '
bz U
bz \
bz t
bz w
bz @
bz O
bz Q
bz V
0*
b1 4
b1 K
b1 g
b10 5
b10 J
b10 b
0(
0;
b1000000000 C
b1000000000 W
b1000000000 d
b1000000000 k
b111 !
b111 &
b111 I
b111 M
1#
#320000
0#
#325000
b100 N
b100 D
b100 r
b1000000000 A
b1000000000 P
b1000000000 l
1%
13
b0 2
b0 L
b0 q
b1000 !
b1000 &
b1000 I
b1000 M
1#
#330000
0#
#335000
b101 N
b101 D
b101 r
b0 A
b0 P
b0 l
03
b10 2
b10 L
b10 q
b1001 !
b1001 &
b1001 I
b1001 M
1#
#340000
0#
#345000
b1 +
b1 S
b1 i
b100 ,
b100 T
b100 c
b101 1
b101 X
b101 u
z6
b101 '
b101 U
b101 \
b101 t
b101 w
1:
1*
b10 4
b10 K
b10 g
b0 5
b0 J
b0 b
0%
b1010 !
b1010 &
b1010 I
b1010 M
1#
#350000
0#
#355000
b111 +
b111 S
b111 i
bz 1
bz X
bz u
16
bz '
bz U
bz \
bz t
bz w
b101 ,
b101 T
b101 c
0*
b0 4
b0 K
b0 g
0:
b101 ?
b101 Y
b101 ^
b101 m
b100 !
b100 &
b100 I
b100 M
1#
#360000
0#
#365000
b1 +
b1 S
b1 i
b110 1
b110 X
b110 u
z6
b110 '
b110 U
b110 \
b110 t
b110 w
b0 @
b0 O
b0 Q
b0 V
18
1*
b10 4
b10 K
b10 g
1(
b0 2
b0 L
b0 q
1<
b101 !
b101 &
b101 I
b101 M
1#
#370000
0#
#375000
b110000100011 @
b110000100011 O
b110000100011 Q
b110000100011 V
b110 N
b110 D
b110 r
1;
b10 2
b10 L
b10 q
08
0<
b110 =
b110 ]
b110 o
b110 !
b110 &
b110 I
b110 M
1#
#380000
0#
#385000
b110000100011 +
b110000100011 S
b110000100011 i
b0 ,
b0 T
b0 c
bz 1
bz X
bz u
16
bz '
bz U
bz \
bz t
bz w
bz @
bz O
bz Q
bz V
0*
b1 4
b1 K
b1 g
b10 5
b10 J
b10 b
0(
0;
b111 !
b111 &
b111 I
b111 M
b110000100011 C
b110000100011 W
b110000100011 d
b110000100011 k
1#
#390000
0#
#395000
b101 N
b101 D
b101 r
b110000100011 A
b110000100011 P
b110000100011 l
1%
13
b0 2
b0 L
b0 q
b1000 !
b1000 &
b1000 I
b1000 M
1#
#400000
0#
#405000
b110 N
b110 D
b110 r
b0 A
b0 P
b0 l
03
b10 2
b10 L
b10 q
b1001 !
b1001 &
b1001 I
b1001 M
1#
#410000
0#
#415000
b1 +
b1 S
b1 i
b101 ,
b101 T
b101 c
b110 1
b110 X
b110 u
z6
b110 '
b110 U
b110 \
b110 t
b110 w
1:
1*
b10 4
b10 K
b10 g
b0 5
b0 J
b0 b
0%
b1010 !
b1010 &
b1010 I
b1010 M
1#
#420000
0#
#425000
b111 +
b111 S
b111 i
bz 1
bz X
bz u
16
bz '
bz U
bz \
bz t
bz w
0*
b0 4
b0 K
b0 g
0:
b110 ,
b110 T
b110 c
b100 !
b100 &
b100 I
b100 M
b110 ?
b110 Y
b110 ^
b110 m
1#
#430000
0#
#435000
b1 +
b1 S
b1 i
b111 1
b111 X
b111 u
z6
b111 '
b111 U
b111 \
b111 t
b111 w
b0 @
b0 O
b0 Q
b0 V
18
1*
b10 4
b10 K
b10 g
1(
b0 2
b0 L
b0 q
1<
b101 !
b101 &
b101 I
b101 M
1#
#440000
0#
#445000
bx @
bx O
bx Q
bx V
b111 N
b111 D
b111 r
1;
b10 2
b10 L
b10 q
08
0<
b110 !
b110 &
b110 I
b110 M
b111 =
b111 ]
b111 o
1#
#450000
0#
#455000
bx +
bx S
bx i
b0 ,
b0 T
b0 c
bz 1
bz X
bz u
x6
bz '
bz U
bz \
bz t
bz w
bz @
bz O
bz Q
bz V
0*
b1 4
b1 K
b1 g
b10 5
b10 J
b10 b
0(
0;
bx C
bx W
bx d
bx k
b111 !
b111 &
b111 I
b111 M
1#
#460000
0#
#465000
b1 +
b1 S
b1 i
b110 ,
b110 T
b110 c
b111 1
b111 X
b111 u
z6
b111 '
b111 U
b111 \
b111 t
b111 w
1:
1*
b10 4
b10 K
b10 g
b0 5
b0 J
b0 b
b1010 !
b1010 &
b1010 I
b1010 M
1#
#470000
0#
#475000
b111 +
b111 S
b111 i
bz 1
bz X
bz u
06
bz '
bz U
bz \
bz t
bz w
b111 ,
b111 T
b111 c
0*
b0 4
b0 K
b0 g
0:
b111 ?
b111 Y
b111 ^
b111 m
b100 !
b100 &
b100 I
b100 M
1#
#480000
0#
#485000
b1 +
b1 S
b1 i
b0 ,
b0 T
b0 c
b1 1
b1 X
b1 u
b1 /
b1 Z
b1 x
z6
b1 '
b1 U
b1 \
b1 t
b1 w
1.
1*
b10 4
b10 K
b10 g
b1 5
b1 J
b1 b
b1011 !
b1011 &
b1011 I
b1011 M
1#
#490000
0#
#495000
b111 +
b111 S
b111 i
bz 1
bz X
bz u
bz /
bz Z
bz x
16
bz '
bz U
bz \
bz t
bz w
0*
b0 4
b0 K
b0 g
b10 !
b10 &
b10 I
b10 M
1#
#500000
0#
#505000
b0 1
b0 X
b0 u
00
1:
b11 !
b11 &
b11 I
b11 M
1#
#510000
0#
#515000
b0 5
b0 J
b0 b
0:
b0 ?
b0 Y
b0 ^
b0 m
b100 !
b100 &
b100 I
b100 M
1#
#520000
0#
#525000
b0 N
b1 +
b1 S
b1 i
b0 D
b0 r
b1 /
b1 Z
b1 x
z6
b1 '
b1 U
b1 \
b1 t
b1 w
b111000000000000 @
b111000000000000 O
b111000000000000 Q
b111000000000000 V
18
1*
b10 4
b10 K
b10 g
1(
b0 2
b0 L
b0 q
1<
b101 !
b101 &
b101 I
b101 M
1#
#530000
0#
#535000
b11010 @
b11010 O
b11010 Q
b11010 V
b1 N
b1 D
b1 r
1;
b10 2
b10 L
b10 q
08
0<
b111000000000000 A
b111000000000000 P
b111000000000000 l
b111000000000000 E
b111000000000000 R
b111000000000000 `
b111000000000000 j
b1 =
b1 ]
b1 o
b110 !
b110 &
b110 I
b110 M
1#
#540000
0#
#545000
b11010 +
b11010 S
b11010 i
b111000000000000 ,
b111000000000000 T
b111000000000000 c
bz /
bz Z
bz x
06
bz '
bz U
bz \
bz t
bz w
bz @
bz O
bz Q
bz V
0*
b1 4
b1 K
b1 g
b10 5
b10 J
b10 b
0(
0;
b111 !
b111 &
b111 I
b111 M
b11010 C
b11010 W
b11010 d
b11010 k
1#
#550000
0#
#555000
b1 +
b1 S
b1 i
b0 ,
b0 T
b0 c
b1 /
b1 Z
b1 x
b1 1
b1 X
b1 u
z6
b1 '
b1 U
b1 \
b1 t
b1 w
1:
10
1*
b10 4
b10 K
b10 g
b0 5
b0 J
b0 b
b1010 !
b1010 &
b1010 I
b1010 M
1#
#560000
0#
#565000
b111 +
b111 S
b111 i
bz 1
bz X
bz u
bz /
bz Z
bz x
16
bz '
bz U
bz \
bz t
bz w
0*
b0 4
b0 K
b0 g
0:
b1 ,
b1 T
b1 c
b100 !
b100 &
b100 I
b100 M
b1 ?
b1 Y
b1 ^
b1 m
1#
#570000
0#
#575000
b1 +
b1 S
b1 i
b10 1
b10 X
b10 u
b10 /
b10 Z
b10 x
z6
b10 '
b10 U
b10 \
b10 t
b10 w
b11010 @
b11010 O
b11010 Q
b11010 V
18
1*
b10 4
b10 K
b10 g
1(
b0 2
b0 L
b0 q
1<
b101 !
b101 &
b101 I
b101 M
1#
#580000
0#
#585000
b10001 @
b10001 O
b10001 Q
b10001 V
b10 N
b10 D
b10 r
1;
b10 2
b10 L
b10 q
08
0<
b11010 A
b11010 P
b11010 l
b110 !
b110 &
b110 I
b110 M
b10 =
b10 ]
b10 o
b11010 E
b11010 R
b11010 `
b11010 j
1#
#590000
0#
#595000
b10001 +
b10001 S
b10001 i
b11010 ,
b11010 T
b11010 c
bz 1
bz X
bz u
bz /
bz Z
bz x
06
bz '
bz U
bz \
bz t
bz w
bz @
bz O
bz Q
bz V
0*
b1 4
b1 K
b1 g
b10 5
b10 J
b10 b
0(
0;
b10001 C
b10001 W
b10001 d
b10001 k
b111 !
b111 &
b111 I
b111 M
1#
#600000
0#
#605000
b1 +
b1 S
b1 i
b1 ,
b1 T
b1 c
b10 1
b10 X
b10 u
b10 /
b10 Z
b10 x
z6
b10 '
b10 U
b10 \
b10 t
b10 w
1:
1*
b10 4
b10 K
b10 g
b0 5
b0 J
b0 b
b1010 !
b1010 &
b1010 I
b1010 M
1#
#610000
0#
#615000
b111 +
b111 S
b111 i
bz 1
bz X
bz u
bz /
bz Z
bz x
16
bz '
bz U
bz \
bz t
bz w
b10 ,
b10 T
b10 c
0*
b0 4
b0 K
b0 g
0:
b10 ?
b10 Y
b10 ^
b10 m
b100 !
b100 &
b100 I
b100 M
1#
#620000
0#
