CONTROL/CONTROL.v
module CONTROL(
    input clk,
    input start,
    input lt,
    output reg rd, wr, operation, clr,preset,
    output reg m3_sel, m5_sel, m6_sel,
    output reg [1:0] m1_sel, m4_sel, m2_sel,
    output reg ln, li, lj, lk, la, lb,
    output [3:0] state_out
);
// output reg state_out

    reg [3:0] state;
    initial begin
        state = 0;
        {rd, wr, operation,clr, preset,m3_sel,m5_sel,m6_sel} = 8'b0;
        m1_sel = 0;
        m4_sel = 0;
        m2_sel = 0;
        {ln,li,lj,lk,la,lb} <= 6'b0;
    end

    always @(*) begin
        case(state)
        0: begin
            {ln,li,lj,lk,la,lb} <= 6'b0;
        end
        1: begin
            clr <= 1;
            m6_sel <= 0;
            lj <= 1;
        end

        2: begin
            clr <=0;
            {ln,li,lj,lk,la,lb} <= 6'b0;
            m1_sel <=1;
            m2_sel <= 0;
            operation <= 0;
        end

        3: begin
            li <= 1;
            m5_sel <= 0;
        end

        4: begin
            {ln,li,lj,lk,la,lb} <= 6'b0;
            m1_sel <= 0;
            m2_sel <= 0;
            operation <= 0;
        end

        5: begin
            la <=1;
            m4_sel <=0;
            rd <= 1;
            m1_sel <= 0;
            m2_sel <= 2;
            operation <= 1;
            lk <= 1;
        end

        6: begin
            la <= 0;
            lk <= 0;
            m4_sel <= 2;
            rd <= 1;
            lb <= 1;
        end

        7: begin
            {ln,li,lj,lk,la,lb} <= 6'b0;
            rd <= 0;
            m1_sel <= 2;
            m2_sel <= 1;
            operation <= 0;
        end

        8: begin
            {ln,li,lj,lk,la,lb} <= 6'b0;
            m4_sel <=0;
            m3_sel <= 1;
            wr <= 1;
        end

        9: begin
            {ln,li,lj,lk,la,lb} <= 6'b0;
            m4_sel <= 2;
            m3_sel <= 0;
            wr <= 1;
        end

        10: begin
            wr <= 0;
            m1_sel <= 0;
            m2_sel <= 2;
            operation <= 1;
            m5_sel <= 1;
            li <= 1;
        end

        11: begin
            li <= 0;
            lj<= 0;
            m1_sel <= 1;
            m2_sel <= 2;
            operation <= 1;
            m6_sel <= 1;
        end

        12: begin
            preset <= 1;
        end

        endcase
    end

    always @(posedge clk) begin
        case(state)

        //RESET STATE
        0: begin
            // {ln,li,lj,lk,la,lb} <= 6'b0;
            if(start) state <= 1;
            else state <= state;
        end

        1: begin
            // clr <= 1;
            // m6_sel <= 0;
            // lj <= 1;
            state <= 2;
        end

        2: begin
            // clr <=0;
            // {ln,li,lj,lk,la,lb} <= 6'b0;
            // m1_sel <=1;
            // m2_sel <= 0;
            // operation <= 0;
            if(lt) state <= 3;
            else state <= 12;
        end

        3: begin
            // li <= 1;
            // m5_sel <= 0;
            state <= 4;
        end

        4: begin
            // {ln,li,lj,lk,la,lb} <= 6'b0;
            // m1_sel <= 0;
            // m2_sel <= 0;
            // operation <= 0;
            if(lt) state <= 5;
            else state <= 11;
        end

        5: begin
            // la <=1;
            // m4_sel <=0;
            // rd <= 1;
            // m1_sel <= 0;
            // m2_sel <= 2;
            // operation <= 1;
            // lk <= 1;
            state <= 6;
        end

        6: begin
            // la <= 0;
            // lk <= 0;
            // m4_sel <= 2;
            // rd <= 1;
            // lb <= 1;
            state <= 7;
        end

        7: begin
            // {ln,li,lj,lk,la,lb} <= 6'b0;
            // rd <= 0;
            // m1_sel <= 2;
            // m2_sel <= 1;
            // operation <= 0;
            if (lt) state <= 8;
            else state <= 10;
        end

        8: begin
            // {ln,li,lj,lk,la,lb} <= 6'b0;
            // m4_sel <=0;
            // m3_sel <= 1;
            // wr <= 1;
            state <= 9;
        end

        9: begin
            // {ln,li,lj,lk,la,lb} <= 6'b0;
            // m4_sel <= 2;
            // m3_sel <= 0;
            // wr <= 1;
            state <= 10;
        end

        10: begin
            // wr <= 0;
            // m1_sel <= 0;
            // m2_sel <= 2;
            // operation <= 1;
            // m5_sel <= 1;
            // li <= 1;
            state <= 4;
        end

        11: begin
            // li <= 0;
            // lj<= 0;
            // m1_sel <= 1;
            // m2_sel <= 2;
            // operation <= 1;
            // m6_sel <= 1;
            state <= 2;
            
        end

        12: begin
            // preset <= 1;
            if(start) state <= state;
            else state <= 0;
        end

        endcase
    end
    // always @(*) begin
    //     state_out <= state;
    // end
    assign state_out = state;



endmodule

CONTROL/CONTROL_TB.v
`timescale 1ns/1ps

module control_tb();

reg clk;
reg start;
reg lt;
wire rd, wr, operation, clr,preset;
wire m3_sel, m5_sel, m6_sel;
wire [1:0] m1_sel, m4_sel, m2_sel;
wire ln, li, lj, lk, la, lb;
wire [3:0] state_out;

initial begin
    $dumpfile("wave.vcd");
    $dumpvars(0,control_tb);
end

CONTROL uut(clk, start,lt,
            rd, wr, operation, clr, preset,
            m3_sel, m5_sel, m6_sel,
            m1_sel, m4_sel, m2_sel,
            ln, li, lj, lk, la, lb,
            state_out
);

initial begin
    clk = 0;
    start = 0;
    lt = 0;

    #2 start = 1; lt = 1;
    #80
    lt = 0;
    #150
    $finish;

end

always clk =#5 ~clk;
endmodule

CONTROL/wave.vcd
$date
	Sun Aug 20 19:29:36 2023
$end
$version
	Icarus Verilog
$end
$timescale
	1ps
$end
$scope module control_tb $end
$var wire 1 ! wr $end
$var wire 4 " state_out [3:0] $end
$var wire 1 # rd $end
$var wire 1 $ preset $end
$var wire 1 % operation $end
$var wire 1 & m6_sel $end
$var wire 1 ' m5_sel $end
$var wire 2 ( m4_sel [1:0] $end
$var wire 1 ) m3_sel $end
$var wire 2 * m2_sel [1:0] $end
$var wire 2 + m1_sel [1:0] $end
$var wire 1 , ln $end
$var wire 1 - lk $end
$var wire 1 . lj $end
$var wire 1 / li $end
$var wire 1 0 lb $end
$var wire 1 1 la $end
$var wire 1 2 clr $end
$var reg 1 3 clk $end
$var reg 1 4 lt $end
$var reg 1 5 start $end
$scope module uut $end
$var wire 1 3 clk $end
$var wire 1 4 lt $end
$var wire 1 5 start $end
$var wire 4 6 state_out [3:0] $end
$var reg 1 2 clr $end
$var reg 1 1 la $end
$var reg 1 0 lb $end
$var reg 1 / li $end
$var reg 1 . lj $end
$var reg 1 - lk $end
$var reg 1 , ln $end
$var reg 2 7 m1_sel [1:0] $end
$var reg 2 8 m2_sel [1:0] $end
$var reg 1 ) m3_sel $end
$var reg 2 9 m4_sel [1:0] $end
$var reg 1 ' m5_sel $end
$var reg 1 & m6_sel $end
$var reg 1 % operation $end
$var reg 1 $ preset $end
$var reg 1 # rd $end
$var reg 4 : state [3:0] $end
$var reg 1 ! wr $end
$upscope $end
$upscope $end
$enddefinitions $end
#0
$dumpvars
b0 :
b0 9
b0 8
b0 7
b0 6
05
04
03
02
01
00
0/
0.
0-
0,
b0 +
b0 *
0)
b0 (
0'
0&
0%
0$
0#
b0 "
0!
$end
#2000
14
15
#5000
1.
12
b1 "
b1 6
b1 :
13
#10000
03
#15000
b1 +
b1 7
0.
02
b10 "
b10 6
b10 :
13
#20000
03
#25000
1/
b11 "
b11 6
b11 :
13
#30000
03
#35000
b0 +
b0 7
0/
b100 "
b100 6
b100 :
13
#40000
03
#45000
1-
1%
b10 *
b10 8
1#
11
b101 "
b101 6
b101 :
13
#50000
03
#55000
10
b10 (
b10 9
0-
01
b110 "
b110 6
b110 :
13
#60000
03
#65000
0%
b1 *
b1 8
b10 +
b10 7
0#
00
b111 "
b111 6
b111 :
13
#70000
03
#75000
1!
1)
b0 (
b0 9
b1000 "
b1000 6
b1000 :
13
#80000
03
#82000
04
#85000
0)
b10 (
b10 9
b1001 "
b1001 6
b1001 :
13
#90000
03
#95000
1/
1'
1%
b10 *
b10 8
b0 +
b0 7
0!
b1010 "
b1010 6
b1010 :
13
#100000
03
#105000
0%
b0 *
b0 8
0/
b100 "
b100 6
b100 :
13
#110000
03
#115000
1&
1%
b10 *
b10 8
b1 +
b1 7
b1011 "
b1011 6
b1011 :
13
#120000
03
#125000
0%
b0 *
b0 8
b10 "
b10 6
b10 :
13
#130000
03
#135000
1$
b1100 "
b1100 6
b1100 :
13
